<?xml version="1.0" encoding="utf-8"?>
<clothing-items>
 <clothing>
  <id>
   219532500
  </id>
  <name>
   Reebok Handbags O-5352
  </name>
  <category>
   Handbags
  </category>
  <size>
   M
  </size>
  <color>
   Синий
  </color>
  <material>
   Кожа
  </material>
  <price>
   204900
  </price>
  <rating>
   3.43
  </rating>
  <reviews>
   486459
  </reviews>
  <exclusive>
   yes
  </exclusive>
 </clothing>
 <clothing>
  <id>
   461116228
  </id>
  <name>
   Vans Jacket B-8301
  </name>
  <category>
   Jacket
  </category>
  <size>
   XXL
  </size>
  <color>
   Голубой
  </color>
  <material>
   Хлопок
  </material>
  <price>
   420991
  </price>
  <rating>
   2.33
  </rating>
  <reviews>
   101657
  </reviews>
  <new>
   -
  </new>
  <exclusive>
   no
  </exclusive>
 </clothing>
 <clothing>
  <id>
   388443238
  </id>
  <name>
   Addidas Handbags W-6504
  </name>
  <category>
   Handbags
  </category>
  <size>
   XXL
  </size>
  <color>
   Красный
  </color>
  <material>
   Шерсть
  </material>
  <price>
   377281
  </price>
  <rating>
   2.71
  </rating>
  <reviews>
   194442
  </reviews>
  <exclusive>
   yes
  </exclusive>
 </clothing>
 <clothing>
  <id>
   713134589
  </id>
  <name>
   Asics Umbrellas D-2244
  </name>
  <category>
   Umbrellas
  </category>
  <size>
   L
  </size>
  <color>
   Голубой
  </color>
  <material>
   Шелк
  </material>
  <price>
   879504
  </price>
  <rating>
   1.83
  </rating>
  <reviews>
   495570
  </reviews>
  <new>
   -
  </new>
  <sporty>
   no
  </sporty>
 </clothing>
 <clothing>
  <id>
   363160114
  </id>
  <name>
   Nike Belts M-4680
  </name>
  <category>
   Belts
  </category>
  <size>
   XL
  </size>
  <color>
   Синий
  </color>
  <material>
   Шелк
  </material>
  <price>
   108299
  </price>
  <rating>
   4.65
  </rating>
  <reviews>
   424616
  </reviews>
  <new>
   -
  </new>
  <exclusive>
   no
  </exclusive>
  <sporty>
   no
  </sporty>
 </clothing>
 <clothing>
  <id>
   260906289
  </id>
  <name>
   PleinSport Shirt R-2658
  </name>
  <category>
   Shirt
  </category>
  <size>
   XXL
  </size>
  <color>
   Желтый
  </color>
  <material>
   Шерсть
  </material>
  <price>
   670238
  </price>
  <rating>
   2.18
  </rating>
  <reviews>
   18629
  </reviews>
 </clothing>
 <clothing>
  <id>
   237238223
  </id>
  <name>
   Adidas Belts C-5061
  </name>
  <category>
   Belts
  </category>
  <size>
   M
  </size>
  <color>
   Желтый
  </color>
  <material>
   Нейлон
  </material>
  <price>
   672211
  </price>
  <rating>
   4.98
  </rating>
  <reviews>
   613173
  </reviews>
  <sporty>
   no
  </sporty>
 </clothing>
 <clothing>
  <id>
   147745118
  </id>
  <name>
   Lacoste Umbrellas E-1286
  </name>
  <category>
   Umbrellas
  </category>
  <size>
   XXL
  </size>
  <color>
   Оранжевый
  </color>
  <material>
   Полиэстер
  </material>
  <price>
   251640
  </price>
  <rating>
   3.82
  </rating>
  <reviews>
   277762
  </reviews>
  <new>
   -
  </new>
  <exclusive>
   yes
  </exclusive>
 </clothing>
 <clothing>
  <id>
   399045049
  </id>
  <name>
   Brooks Skirt G-3128
  </name>
  <category>
   Skirt
  </category>
  <size>
   M
  </size>
  <color>
   Голубой
  </color>
  <material>
   Вискоза
  </material>
  <price>
   210921
  </price>
  <rating>
   1.88
  </rating>
  <reviews>
   378201
  </reviews>
  <exclusive>
   no
  </exclusive>
  <sporty>
   yes
  </sporty>
 </clothing>
 <clothing>
  <id>
   864476295
  </id>
  <name>
   Under Armour T-shirt S-8930
  </name>
  <category>
   T-shirt
  </category>
  <size>
   L
  </size>
  <color>
   Голубой
  </color>
  <material>
   Хлопок
  </material>
  <price>
   675448
  </price>
  <rating>
   3.58
  </rating>
  <reviews>
   800739
  </reviews>
  <sporty>
   no
  </sporty>
 </clothing>
 <clothing>
  <id>
   960336818
  </id>
  <name>
   Asics Shoes P-1950
  </name>
  <category>
   Shoes
  </category>
  <size>
   L
  </size>
  <color>
   Желтый
  </color>
  <material>
   Нейлон
  </material>
  <price>
   711815
  </price>
  <rating>
   1.15
  </rating>
  <reviews>
   923318
  </reviews>
  <new>
   -
  </new>
  <exclusive>
   yes
  </exclusive>
 </clothing>
 <clothing>
  <id>
   539716482
  </id>
  <name>
   PleinSport Jeans F-8969
  </name>
  <category>
   Jeans
  </category>
  <size>
   L
  </size>
  <color>
   Желтый
  </color>
  <material>
   Шерсть
  </material>
  <price>
   402795
  </price>
  <rating>
   4.79
  </rating>
  <reviews>
   639019
  </reviews>
  <new>
   -
  </new>
  <exclusive>
   no
  </exclusive>
 </clothing>
 <clothing>
  <id>
   705326493
  </id>
  <name>
   Nike Sweater I-7150
  </name>
  <category>
   Sweater
  </category>
  <size>
   S
  </size>
  <color>
   Оранжевый
  </color>
  <material>
   Нейлон
  </material>
  <price>
   614973
  </price>
  <rating>
   1.62
  </rating>
  <reviews>
   927260
  </reviews>
  <new>
   +
  </new>
  <exclusive>
   no
  </exclusive>
 </clothing>
 <clothing>
  <id>
   652809132
  </id>
  <name>
   Asics Pants R-6081
  </name>
  <category>
   Pants
  </category>
  <size>
   S
  </size>
  <color>
   Оранжевый
  </color>
  <material>
   Шелк
  </material>
  <price>
   728715
  </price>
  <rating>
   3.14
  </rating>
  <reviews>
   481768
  </reviews>
  <exclusive>
   yes
  </exclusive>
  <sporty>
   no
  </sporty>
 </clothing>
 <clothing>
  <id>
   109884908
  </id>
  <name>
   Puma Shoes H-9318
  </name>
  <category>
   Shoes
  </category>
  <size>
   S
  </size>
  <color>
   Голубой
  </color>
  <material>
   Вискоза
  </material>
  <price>
   774482
  </price>
  <rating>
   3.5
  </rating>
  <reviews>
   533583
  </reviews>
  <exclusive>
   yes
  </exclusive>
 </clothing>
 <clothing>
  <id>
   464915475
  </id>
  <name>
   Ellesse Shoes P-2094
  </name>
  <category>
   Shoes
  </category>
  <size>
   M
  </size>
  <color>
   Красный
  </color>
  <material>
   Шерсть
  </material>
  <price>
   710855
  </price>
  <rating>
   4.93
  </rating>
  <reviews>
   660567
  </reviews>
  <new>
   +
  </new>
  <exclusive>
   no
  </exclusive>
 </clothing>
 <clothing>
  <id>
   344841240
  </id>
  <name>
   Fila Belts C-7316
  </name>
  <category>
   Belts
  </category>
  <size>
   XL
  </size>
  <color>
   Синий
  </color>
  <material>
   Полиэстер
  </material>
  <price>
   675584
  </price>
  <rating>
   2.87
  </rating>
  <reviews>
   737978
  </reviews>
  <new>
   +
  </new>
  <exclusive>
   yes
  </exclusive>
  <sporty>
   yes
  </sporty>
 </clothing>
 <clothing>
  <id>
   128139463
  </id>
  <name>
   Ellesse Blouse V-7698
  </name>
  <category>
   Blouse
  </category>
  <size>
   XXL
  </size>
  <color>
   Голубой
  </color>
  <material>
   Шелк
  </material>
  <price>
   258701
  </price>
  <rating>
   4.29
  </rating>
  <reviews>
   892160
  </reviews>
  <new>
   +
  </new>
 </clothing>
 <clothing>
  <id>
   697488413
  </id>
  <name>
   PleinSport Dress K-8717
  </name>
  <category>
   Dress
  </category>
  <size>
   XL
  </size>
  <color>
   Желтый
  </color>
  <material>
   Нейлон
  </material>
  <price>
   826379
  </price>
  <rating>
   2.89
  </rating>
  <reviews>
   311719
  </reviews>
  <new>
   -
  </new>
 </clothing>
 <clothing>
  <id>
   715265803
  </id>
  <name>
   Brooks Pants D-6340
  </name>
  <category>
   Pants
  </category>
  <size>
   S
  </size>
  <color>
   Синий
  </color>
  <material>
   Нейлон
  </material>
  <price>
   377548
  </price>
  <rating>
   2.19
  </rating>
  <reviews>
   277151
  </reviews>
  <new>
   -
  </new>
  <sporty>
   no
  </sporty>
 </clothing>
 <clothing>
  <id>
   662203557
  </id>
  <name>
   PleinSport Dress Q-4176
  </name>
  <category>
   Dress
  </category>
  <size>
   L
  </size>
  <color>
   Желтый
  </color>
  <material>
   Шелк
  </material>
  <price>
   317203
  </price>
  <rating>
   4.98
  </rating>
  <reviews>
   915539
  </reviews>
  <new>
   -
  </new>
  <exclusive>
   no
  </exclusive>
 </clothing>
 <clothing>
  <id>
   845067880
  </id>
  <name>
   PleinSport Blouse S-3604
  </name>
  <category>
   Blouse
  </category>
  <size>
   L
  </size>
  <color>
   Фиолетовый
  </color>
  <material>
   Вискоза
  </material>
  <price>
   479550
  </price>
  <rating>
   1.0
  </rating>
  <reviews>
   594796
  </reviews>
  <exclusive>
   no
  </exclusive>
  <sporty>
   no
  </sporty>
 </clothing>
 <clothing>
  <id>
   686034429
  </id>
  <name>
   New Balance Jacket B-8278
  </name>
  <category>
   Jacket
  </category>
  <size>
   S
  </size>
  <color>
   Красный
  </color>
  <material>
   Хлопок
  </material>
  <price>
   430680
  </price>
  <rating>
   1.39
  </rating>
  <reviews>
   968214
  </reviews>
  <new>
   +
  </new>
  <exclusive>
   yes
  </exclusive>
  <sporty>
   no
  </sporty>
 </clothing>
 <clothing>
  <id>
   165497167
  </id>
  <name>
   DC Sweater X-7368
  </name>
  <category>
   Sweater
  </category>
  <size>
   M
  </size>
  <color>
   Оранжевый
  </color>
  <material>
   Шерсть
  </material>
  <price>
   187202
  </price>
  <rating>
   2.81
  </rating>
  <reviews>
   832231
  </reviews>
  <new>
   +
  </new>
  <sporty>
   yes
  </sporty>
 </clothing>
 <clothing>
  <id>
   439695911
  </id>
  <name>
   Reebok Handbags E-5672
  </name>
  <category>
   Handbags
  </category>
  <size>
   XXL
  </size>
  <color>
   Оранжевый
  </color>
  <material>
   Полиэстер
  </material>
  <price>
   660232
  </price>
  <rating>
   2.56
  </rating>
  <reviews>
   989243
  </reviews>
  <new>
   +
  </new>
  <exclusive>
   no
  </exclusive>
  <sporty>
   no
  </sporty>
 </clothing>
 <clothing>
  <id>
   924176044
  </id>
  <name>
   Puma Umbrellas A-4226
  </name>
  <category>
   Umbrellas
  </category>
  <size>
   L
  </size>
  <color>
   Фиолетовый
  </color>
  <material>
   Полиэстер
  </material>
  <price>
   208295
  </price>
  <rating>
   3.4
  </rating>
  <reviews>
   48840
  </reviews>
  <new>
   -
  </new>
 </clothing>
 <clothing>
  <id>
   481086283
  </id>
  <name>
   Adidas Gloves V-8781
  </name>
  <category>
   Gloves
  </category>
  <size>
   M
  </size>
  <color>
   Желтый
  </color>
  <material>
   Шерсть
  </material>
  <price>
   707718
  </price>
  <rating>
   3.81
  </rating>
  <reviews>
   663970
  </reviews>
  <new>
   +
  </new>
 </clothing>
 <clothing>
  <id>
   452562956
  </id>
  <name>
   Adidas Hat J-6039
  </name>
  <category>
   Hat
  </category>
  <size>
   XL
  </size>
  <color>
   Желтый
  </color>
  <material>
   Лен
  </material>
  <price>
   258827
  </price>
  <rating>
   3.29
  </rating>
  <reviews>
   292207
  </reviews>
  <new>
   -
  </new>
  <exclusive>
   no
  </exclusive>
 </clothing>
 <clothing>
  <id>
   732006001
  </id>
  <name>
   Converse Jacket V-6348
  </name>
  <category>
   Jacket
  </category>
  <size>
   XXL
  </size>
  <color>
   Синий
  </color>
  <material>
   Кожа
  </material>
  <price>
   638031
  </price>
  <rating>
   2.62
  </rating>
  <reviews>
   700508
  </reviews>
  <new>
   -
  </new>
  <exclusive>
   no
  </exclusive>
  <sporty>
   no
  </sporty>
 </clothing>
 <clothing>
  <id>
   538225410
  </id>
  <name>
   Nike Jeans M-7443
  </name>
  <category>
   Jeans
  </category>
  <size>
   L
  </size>
  <color>
   Желтый
  </color>
  <material>
   Полиэстер
  </material>
  <price>
   299151
  </price>
  <rating>
   3.54
  </rating>
  <reviews>
   808366
  </reviews>
  <exclusive>
   no
  </exclusive>
  <sporty>
   no
  </sporty>
 </clothing>
 <clothing>
  <id>
   352325795
  </id>
  <name>
   Reebok Hat G-1963
  </name>
  <category>
   Hat
  </category>
  <size>
   S
  </size>
  <color>
   Зеленый
  </color>
  <material>
   Лен
  </material>
  <price>
   340974
  </price>
  <rating>
   1.09
  </rating>
  <reviews>
   586397
  </reviews>
 </clothing>
 <clothing>
  <id>
   440087881
  </id>
  <name>
   Ellesse Jacket S-3761
  </name>
  <category>
   Jacket
  </category>
  <size>
   S
  </size>
  <color>
   Желтый
  </color>
  <material>
   Шелк
  </material>
  <price>
   908833
  </price>
  <rating>
   1.42
  </rating>
  <reviews>
   304276
  </reviews>
  <sporty>
   yes
  </sporty>
 </clothing>
 <clothing>
  <id>
   877094956
  </id>
  <name>
   Lacoste T-shirt T-9621
  </name>
  <category>
   T-shirt
  </category>
  <size>
   S
  </size>
  <color>
   Желтый
  </color>
  <material>
   Полиэстер
  </material>
  <price>
   385249
  </price>
  <rating>
   3.15
  </rating>
  <reviews>
   66107
  </reviews>
  <exclusive>
   yes
  </exclusive>
 </clothing>
 <clothing>
  <id>
   309775591
  </id>
  <name>
   DC Shoes G-1647
  </name>
  <category>
   Shoes
  </category>
  <size>
   L
  </size>
  <color>
   Красный
  </color>
  <material>
   Шерсть
  </material>
  <price>
   271387
  </price>
  <rating>
   2.67
  </rating>
  <reviews>
   859451
  </reviews>
  <exclusive>
   no
  </exclusive>
 </clothing>
 <clothing>
  <id>
   179290260
  </id>
  <name>
   PleinSport T-shirt J-6690
  </name>
  <category>
   T-shirt
  </category>
  <size>
   XL
  </size>
  <color>
   Красный
  </color>
  <material>
   Шерсть
  </material>
  <price>
   409300
  </price>
  <rating>
   4.88
  </rating>
  <reviews>
   773967
  </reviews>
  <exclusive>
   no
  </exclusive>
  <sporty>
   yes
  </sporty>
 </clothing>
 <clothing>
  <id>
   913340746
  </id>
  <name>
   Addidas Blouse H-3914
  </name>
  <category>
   Blouse
  </category>
  <size>
   XL
  </size>
  <color>
   Фиолетовый
  </color>
  <material>
   Кожа
  </material>
  <price>
   567277
  </price>
  <rating>
   1.17
  </rating>
  <reviews>
   958789
  </reviews>
  <sporty>
   no
  </sporty>
 </clothing>
 <clothing>
  <id>
   127502682
  </id>
  <name>
   New Balance Hat Q-3004
  </name>
  <category>
   Hat
  </category>
  <size>
   XXL
  </size>
  <color>
   Оранжевый
  </color>
  <material>
   Кожа
  </material>
  <price>
   704008
  </price>
  <rating>
   4.4
  </rating>
  <reviews>
   879073
  </reviews>
 </clothing>
 <clothing>
  <id>
   741055477
  </id>
  <name>
   Nike Handbags W-7223
  </name>
  <category>
   Handbags
  </category>
  <size>
   XXL
  </size>
  <color>
   Оранжевый
  </color>
  <material>
   Лен
  </material>
  <price>
   452430
  </price>
  <rating>
   2.34
  </rating>
  <reviews>
   470047
  </reviews>
  <new>
   -
  </new>
  <exclusive>
   no
  </exclusive>
 </clothing>
 <clothing>
  <id>
   914805280
  </id>
  <name>
   Fila Socks F-3369
  </name>
  <category>
   Socks
  </category>
  <size>
   L
  </size>
  <color>
   Оранжевый
  </color>
  <material>
   Лен
  </material>
  <price>
   409893
  </price>
  <rating>
   4.39
  </rating>
  <reviews>
   227344
  </reviews>
  <new>
   +
  </new>
  <sporty>
   no
  </sporty>
 </clothing>
 <clothing>
  <id>
   207332007
  </id>
  <name>
   PleinSport Blouse F-5586
  </name>
  <category>
   Blouse
  </category>
  <size>
   S
  </size>
  <color>
   Фиолетовый
  </color>
  <material>
   Шерсть
  </material>
  <price>
   672222
  </price>
  <rating>
   3.88
  </rating>
  <reviews>
   159564
  </reviews>
  <new>
   +
  </new>
  <exclusive>
   no
  </exclusive>
  <sporty>
   yes
  </sporty>
 </clothing>
 <clothing>
  <id>
   630102279
  </id>
  <name>
   Addidas Shirt B-4331
  </name>
  <category>
   Shirt
  </category>
  <size>
   L
  </size>
  <color>
   Фиолетовый
  </color>
  <material>
   Хлопок
  </material>
  <price>
   573810
  </price>
  <rating>
   1.61
  </rating>
  <reviews>
   311813
  </reviews>
  <sporty>
   no
  </sporty>
 </clothing>
 <clothing>
  <id>
   769665711
  </id>
  <name>
   New Balance Umbrellas B-7886
  </name>
  <category>
   Umbrellas
  </category>
  <size>
   M
  </size>
  <color>
   Синий
  </color>
  <material>
   Вискоза
  </material>
  <price>
   687705
  </price>
  <rating>
   1.55
  </rating>
  <reviews>
   863279
  </reviews>
 </clothing>
 <clothing>
  <id>
   663558506
  </id>
  <name>
   Addidas Gloves R-1405
  </name>
  <category>
   Gloves
  </category>
  <size>
   XL
  </size>
  <color>
   Синий
  </color>
  <material>
   Шерсть
  </material>
  <price>
   841739
  </price>
  <rating>
   1.37
  </rating>
  <reviews>
   351396
  </reviews>
  <new>
   -
  </new>
  <sporty>
   yes
  </sporty>
 </clothing>
 <clothing>
  <id>
   432162896
  </id>
  <name>
   Reebok Socks X-9298
  </name>
  <category>
   Socks
  </category>
  <size>
   XL
  </size>
  <color>
   Оранжевый
  </color>
  <material>
   Шерсть
  </material>
  <price>
   141793
  </price>
  <rating>
   4.3
  </rating>
  <reviews>
   721401
  </reviews>
  <sporty>
   no
  </sporty>
 </clothing>
 <clothing>
  <id>
   619645702
  </id>
  <name>
   Vans Hat K-5718
  </name>
  <category>
   Hat
  </category>
  <size>
   S
  </size>
  <color>
   Красный
  </color>
  <material>
   Вискоза
  </material>
  <price>
   631250
  </price>
  <rating>
   1.14
  </rating>
  <reviews>
   151534
  </reviews>
  <new>
   +
  </new>
  <exclusive>
   no
  </exclusive>
  <sporty>
   yes
  </sporty>
 </clothing>
</clothing-items>
