<?xml version="1.0" encoding="utf-8"?>
<clothing-items>
 <clothing>
  <id>
   157492154
  </id>
  <name>
   Addidas Shoes Z-1238
  </name>
  <category>
   Shoes
  </category>
  <size>
   M
  </size>
  <color>
   Голубой
  </color>
  <material>
   Нейлон
  </material>
  <price>
   579368
  </price>
  <rating>
   3.41
  </rating>
  <reviews>
   738168
  </reviews>
  <new>
   +
  </new>
  <exclusive>
   no
  </exclusive>
  <sporty>
   yes
  </sporty>
 </clothing>
 <clothing>
  <id>
   681741293
  </id>
  <name>
   PleinSport Gloves F-4548
  </name>
  <category>
   Gloves
  </category>
  <size>
   XXL
  </size>
  <color>
   Красный
  </color>
  <material>
   Шелк
  </material>
  <price>
   681348
  </price>
  <rating>
   1.96
  </rating>
  <reviews>
   598413
  </reviews>
  <exclusive>
   no
  </exclusive>
 </clothing>
 <clothing>
  <id>
   698363552
  </id>
  <name>
   Converse Gloves G-9155
  </name>
  <category>
   Gloves
  </category>
  <size>
   XL
  </size>
  <color>
   Синий
  </color>
  <material>
   Вискоза
  </material>
  <price>
   267440
  </price>
  <rating>
   3.33
  </rating>
  <reviews>
   451476
  </reviews>
  <exclusive>
   no
  </exclusive>
 </clothing>
 <clothing>
  <id>
   205593831
  </id>
  <name>
   Addidas Hat X-3591
  </name>
  <category>
   Hat
  </category>
  <size>
   S
  </size>
  <color>
   Красный
  </color>
  <material>
   Вискоза
  </material>
  <price>
   239340
  </price>
  <rating>
   2.74
  </rating>
  <reviews>
   687567
  </reviews>
  <sporty>
   no
  </sporty>
 </clothing>
 <clothing>
  <id>
   430899906
  </id>
  <name>
   Reebok Gloves C-1466
  </name>
  <category>
   Gloves
  </category>
  <size>
   XL
  </size>
  <color>
   Оранжевый
  </color>
  <material>
   Шелк
  </material>
  <price>
   822492
  </price>
  <rating>
   2.26
  </rating>
  <reviews>
   491381
  </reviews>
  <exclusive>
   yes
  </exclusive>
 </clothing>
 <clothing>
  <id>
   688257775
  </id>
  <name>
   Nike Socks A-4433
  </name>
  <category>
   Socks
  </category>
  <size>
   L
  </size>
  <color>
   Желтый
  </color>
  <material>
   Лен
  </material>
  <price>
   429498
  </price>
  <rating>
   3.15
  </rating>
  <reviews>
   173150
  </reviews>
  <new>
   -
  </new>
  <exclusive>
   no
  </exclusive>
  <sporty>
   yes
  </sporty>
 </clothing>
 <clothing>
  <id>
   200686437
  </id>
  <name>
   Reebok Skirt B-3401
  </name>
  <category>
   Skirt
  </category>
  <size>
   XL
  </size>
  <color>
   Красный
  </color>
  <material>
   Нейлон
  </material>
  <price>
   409725
  </price>
  <rating>
   1.41
  </rating>
  <reviews>
   433573
  </reviews>
  <sporty>
   yes
  </sporty>
 </clothing>
 <clothing>
  <id>
   396938632
  </id>
  <name>
   Adidas Pants G-3198
  </name>
  <category>
   Pants
  </category>
  <size>
   L
  </size>
  <color>
   Желтый
  </color>
  <material>
   Хлопок
  </material>
  <price>
   474307
  </price>
  <rating>
   4.25
  </rating>
  <reviews>
   953673
  </reviews>
  <sporty>
   yes
  </sporty>
 </clothing>
 <clothing>
  <id>
   222389846
  </id>
  <name>
   Nike Jeans V-5692
  </name>
  <category>
   Jeans
  </category>
  <size>
   XXL
  </size>
  <color>
   Желтый
  </color>
  <material>
   Нейлон
  </material>
  <price>
   555370
  </price>
  <rating>
   4.83
  </rating>
  <reviews>
   358651
  </reviews>
  <new>
   +
  </new>
  <sporty>
   no
  </sporty>
 </clothing>
 <clothing>
  <id>
   479558589
  </id>
  <name>
   Fila Belts C-2372
  </name>
  <category>
   Belts
  </category>
  <size>
   XXL
  </size>
  <color>
   Желтый
  </color>
  <material>
   Шелк
  </material>
  <price>
   394056
  </price>
  <rating>
   2.7
  </rating>
  <reviews>
   591217
  </reviews>
  <exclusive>
   no
  </exclusive>
  <sporty>
   yes
  </sporty>
 </clothing>
 <clothing>
  <id>
   535927723
  </id>
  <name>
   Vans Shoes O-6214
  </name>
  <category>
   Shoes
  </category>
  <size>
   XL
  </size>
  <color>
   Красный
  </color>
  <material>
   Шерсть
  </material>
  <price>
   796025
  </price>
  <rating>
   3.94
  </rating>
  <reviews>
   310999
  </reviews>
  <exclusive>
   no
  </exclusive>
  <sporty>
   no
  </sporty>
 </clothing>
 <clothing>
  <id>
   881503277
  </id>
  <name>
   Brooks Pants S-9592
  </name>
  <category>
   Pants
  </category>
  <size>
   M
  </size>
  <color>
   Синий
  </color>
  <material>
   Шерсть
  </material>
  <price>
   412385
  </price>
  <rating>
   3.04
  </rating>
  <reviews>
   46455
  </reviews>
  <sporty>
   yes
  </sporty>
 </clothing>
 <clothing>
  <id>
   936850704
  </id>
  <name>
   Reebok Blouse K-1978
  </name>
  <category>
   Blouse
  </category>
  <size>
   S
  </size>
  <color>
   Голубой
  </color>
  <material>
   Нейлон
  </material>
  <price>
   292395
  </price>
  <rating>
   2.13
  </rating>
  <reviews>
   268705
  </reviews>
  <new>
   +
  </new>
  <sporty>
   no
  </sporty>
 </clothing>
 <clothing>
  <id>
   204221069
  </id>
  <name>
   Addidas Sweater Z-5025
  </name>
  <category>
   Sweater
  </category>
  <size>
   S
  </size>
  <color>
   Голубой
  </color>
  <material>
   Шелк
  </material>
  <price>
   136510
  </price>
  <rating>
   1.36
  </rating>
  <reviews>
   377840
  </reviews>
  <sporty>
   yes
  </sporty>
 </clothing>
 <clothing>
  <id>
   963949653
  </id>
  <name>
   Lacoste Pants R-7663
  </name>
  <category>
   Pants
  </category>
  <size>
   M
  </size>
  <color>
   Оранжевый
  </color>
  <material>
   Шерсть
  </material>
  <price>
   904719
  </price>
  <rating>
   3.97
  </rating>
  <reviews>
   660968
  </reviews>
  <sporty>
   no
  </sporty>
 </clothing>
 <clothing>
  <id>
   902726132
  </id>
  <name>
   Adidas Socks R-2834
  </name>
  <category>
   Socks
  </category>
  <size>
   S
  </size>
  <color>
   Красный
  </color>
  <material>
   Хлопок
  </material>
  <price>
   496118
  </price>
  <rating>
   2.67
  </rating>
  <reviews>
   762796
  </reviews>
  <new>
   -
  </new>
  <sporty>
   yes
  </sporty>
 </clothing>
 <clothing>
  <id>
   971281764
  </id>
  <name>
   Fila Shoes L-6021
  </name>
  <category>
   Shoes
  </category>
  <size>
   L
  </size>
  <color>
   Фиолетовый
  </color>
  <material>
   Полиэстер
  </material>
  <price>
   835416
  </price>
  <rating>
   2.81
  </rating>
  <reviews>
   903188
  </reviews>
  <new>
   -
  </new>
  <exclusive>
   yes
  </exclusive>
 </clothing>
 <clothing>
  <id>
   389869935
  </id>
  <name>
   DC Sweater J-3525
  </name>
  <category>
   Sweater
  </category>
  <size>
   XXL
  </size>
  <color>
   Синий
  </color>
  <material>
   Полиэстер
  </material>
  <price>
   970844
  </price>
  <rating>
   1.9
  </rating>
  <reviews>
   372210
  </reviews>
  <sporty>
   yes
  </sporty>
 </clothing>
 <clothing>
  <id>
   615524457
  </id>
  <name>
   Ellesse Pants L-6579
  </name>
  <category>
   Pants
  </category>
  <size>
   M
  </size>
  <color>
   Желтый
  </color>
  <material>
   Нейлон
  </material>
  <price>
   175082
  </price>
  <rating>
   3.73
  </rating>
  <reviews>
   830614
  </reviews>
  <new>
   -
  </new>
  <exclusive>
   no
  </exclusive>
  <sporty>
   yes
  </sporty>
 </clothing>
 <clothing>
  <id>
   397357737
  </id>
  <name>
   New Balance Skirt V-3824
  </name>
  <category>
   Skirt
  </category>
  <size>
   L
  </size>
  <color>
   Оранжевый
  </color>
  <material>
   Шерсть
  </material>
  <price>
   784375
  </price>
  <rating>
   4.83
  </rating>
  <reviews>
   447255
  </reviews>
  <exclusive>
   yes
  </exclusive>
  <sporty>
   no
  </sporty>
 </clothing>
 <clothing>
  <id>
   487067278
  </id>
  <name>
   Addidas Umbrellas I-1366
  </name>
  <category>
   Umbrellas
  </category>
  <size>
   L
  </size>
  <color>
   Оранжевый
  </color>
  <material>
   Лен
  </material>
  <price>
   871654
  </price>
  <rating>
   3.57
  </rating>
  <reviews>
   346791
  </reviews>
  <sporty>
   yes
  </sporty>
 </clothing>
</clothing-items>
