<?xml version="1.0" encoding="utf-8"?>
<clothing-items>
 <clothing>
  <id>
   127184341
  </id>
  <name>
   Under Armour Jacket Y-1070
  </name>
  <category>
   Jacket
  </category>
  <size>
   XL
  </size>
  <color>
   Голубой
  </color>
  <material>
   Хлопок
  </material>
  <price>
   668560
  </price>
  <rating>
   1.78
  </rating>
  <reviews>
   160553
  </reviews>
  <new>
   +
  </new>
  <exclusive>
   yes
  </exclusive>
  <sporty>
   yes
  </sporty>
 </clothing>
 <clothing>
  <id>
   698916431
  </id>
  <name>
   Puma Socks T-9037
  </name>
  <category>
   Socks
  </category>
  <size>
   M
  </size>
  <color>
   Оранжевый
  </color>
  <material>
   Полиэстер
  </material>
  <price>
   681711
  </price>
  <rating>
   4.77
  </rating>
  <reviews>
   875712
  </reviews>
  <new>
   -
  </new>
  <exclusive>
   yes
  </exclusive>
 </clothing>
 <clothing>
  <id>
   171947604
  </id>
  <name>
   Reebok Hat C-6730
  </name>
  <category>
   Hat
  </category>
  <size>
   XXL
  </size>
  <color>
   Синий
  </color>
  <material>
   Лен
  </material>
  <price>
   525899
  </price>
  <rating>
   3.73
  </rating>
  <reviews>
   132091
  </reviews>
 </clothing>
 <clothing>
  <id>
   380916275
  </id>
  <name>
   Puma Jeans Z-1795
  </name>
  <category>
   Jeans
  </category>
  <size>
   M
  </size>
  <color>
   Красный
  </color>
  <material>
   Шерсть
  </material>
  <price>
   814677
  </price>
  <rating>
   4.13
  </rating>
  <reviews>
   252609
  </reviews>
  <new>
   -
  </new>
 </clothing>
 <clothing>
  <id>
   307179514
  </id>
  <name>
   Brooks T-shirt T-6007
  </name>
  <category>
   T-shirt
  </category>
  <size>
   XXL
  </size>
  <color>
   Голубой
  </color>
  <material>
   Полиэстер
  </material>
  <price>
   317105
  </price>
  <rating>
   2.93
  </rating>
  <reviews>
   219377
  </reviews>
  <new>
   +
  </new>
  <exclusive>
   yes
  </exclusive>
  <sporty>
   no
  </sporty>
 </clothing>
 <clothing>
  <id>
   735353686
  </id>
  <name>
   Vans Jacket Y-3249
  </name>
  <category>
   Jacket
  </category>
  <size>
   M
  </size>
  <color>
   Зеленый
  </color>
  <material>
   Лен
  </material>
  <price>
   430796
  </price>
  <rating>
   3.5
  </rating>
  <reviews>
   114737
  </reviews>
  <new>
   -
  </new>
  <sporty>
   yes
  </sporty>
 </clothing>
 <clothing>
  <id>
   272014705
  </id>
  <name>
   Converse Gloves N-3193
  </name>
  <category>
   Gloves
  </category>
  <size>
   L
  </size>
  <color>
   Синий
  </color>
  <material>
   Кожа
  </material>
  <price>
   746182
  </price>
  <rating>
   2.85
  </rating>
  <reviews>
   683461
  </reviews>
  <new>
   -
  </new>
  <exclusive>
   no
  </exclusive>
  <sporty>
   no
  </sporty>
 </clothing>
 <clothing>
  <id>
   182964415
  </id>
  <name>
   Adidas Jeans H-7352
  </name>
  <category>
   Jeans
  </category>
  <size>
   S
  </size>
  <color>
   Фиолетовый
  </color>
  <material>
   Хлопок
  </material>
  <price>
   971307
  </price>
  <rating>
   3.0
  </rating>
  <reviews>
   364014
  </reviews>
  <exclusive>
   yes
  </exclusive>
 </clothing>
 <clothing>
  <id>
   129179720
  </id>
  <name>
   Nike Jeans R-7333
  </name>
  <category>
   Jeans
  </category>
  <size>
   XXL
  </size>
  <color>
   Фиолетовый
  </color>
  <material>
   Полиэстер
  </material>
  <price>
   910800
  </price>
  <rating>
   2.83
  </rating>
  <reviews>
   172808
  </reviews>
  <exclusive>
   no
  </exclusive>
 </clothing>
 <clothing>
  <id>
   485642356
  </id>
  <name>
   Lacoste Skirt Y-8410
  </name>
  <category>
   Skirt
  </category>
  <size>
   XL
  </size>
  <color>
   Зеленый
  </color>
  <material>
   Шерсть
  </material>
  <price>
   722642
  </price>
  <rating>
   2.44
  </rating>
  <reviews>
   783130
  </reviews>
  <new>
   -
  </new>
  <exclusive>
   no
  </exclusive>
  <sporty>
   no
  </sporty>
 </clothing>
 <clothing>
  <id>
   875777457
  </id>
  <name>
   PleinSport Skirt F-1702
  </name>
  <category>
   Skirt
  </category>
  <size>
   M
  </size>
  <color>
   Фиолетовый
  </color>
  <material>
   Хлопок
  </material>
  <price>
   611930
  </price>
  <rating>
   3.2
  </rating>
  <reviews>
   793060
  </reviews>
  <new>
   -
  </new>
  <exclusive>
   no
  </exclusive>
  <sporty>
   no
  </sporty>
 </clothing>
 <clothing>
  <id>
   597613824
  </id>
  <name>
   Lacoste Dress I-7141
  </name>
  <category>
   Dress
  </category>
  <size>
   XL
  </size>
  <color>
   Голубой
  </color>
  <material>
   Кожа
  </material>
  <price>
   379821
  </price>
  <rating>
   2.49
  </rating>
  <reviews>
   46819
  </reviews>
  <new>
   -
  </new>
  <exclusive>
   no
  </exclusive>
  <sporty>
   yes
  </sporty>
 </clothing>
 <clothing>
  <id>
   455807416
  </id>
  <name>
   Under Armour Socks S-8660
  </name>
  <category>
   Socks
  </category>
  <size>
   L
  </size>
  <color>
   Фиолетовый
  </color>
  <material>
   Полиэстер
  </material>
  <price>
   218834
  </price>
  <rating>
   2.13
  </rating>
  <reviews>
   386907
  </reviews>
  <exclusive>
   no
  </exclusive>
  <sporty>
   no
  </sporty>
 </clothing>
 <clothing>
  <id>
   534855726
  </id>
  <name>
   Asics Jacket C-7152
  </name>
  <category>
   Jacket
  </category>
  <size>
   XXL
  </size>
  <color>
   Голубой
  </color>
  <material>
   Лен
  </material>
  <price>
   514479
  </price>
  <rating>
   2.6
  </rating>
  <reviews>
   315533
  </reviews>
  <sporty>
   yes
  </sporty>
 </clothing>
 <clothing>
  <id>
   417812128
  </id>
  <name>
   Addidas Gloves W-7128
  </name>
  <category>
   Gloves
  </category>
  <size>
   M
  </size>
  <color>
   Оранжевый
  </color>
  <material>
   Кожа
  </material>
  <price>
   413962
  </price>
  <rating>
   4.44
  </rating>
  <reviews>
   376182
  </reviews>
  <exclusive>
   yes
  </exclusive>
 </clothing>
 <clothing>
  <id>
   639160257
  </id>
  <name>
   Ellesse Skirt U-9834
  </name>
  <category>
   Skirt
  </category>
  <size>
   XXL
  </size>
  <color>
   Оранжевый
  </color>
  <material>
   Нейлон
  </material>
  <price>
   211300
  </price>
  <rating>
   4.67
  </rating>
  <reviews>
   640664
  </reviews>
  <new>
   -
  </new>
  <sporty>
   no
  </sporty>
 </clothing>
 <clothing>
  <id>
   815595422
  </id>
  <name>
   Puma Socks P-1144
  </name>
  <category>
   Socks
  </category>
  <size>
   S
  </size>
  <color>
   Красный
  </color>
  <material>
   Шелк
  </material>
  <price>
   149356
  </price>
  <rating>
   4.62
  </rating>
  <reviews>
   810167
  </reviews>
  <new>
   +
  </new>
 </clothing>
 <clothing>
  <id>
   190911129
  </id>
  <name>
   Fila Pants K-4224
  </name>
  <category>
   Pants
  </category>
  <size>
   XXL
  </size>
  <color>
   Голубой
  </color>
  <material>
   Кожа
  </material>
  <price>
   215409
  </price>
  <rating>
   2.91
  </rating>
  <reviews>
   499676
  </reviews>
  <sporty>
   no
  </sporty>
 </clothing>
 <clothing>
  <id>
   971092278
  </id>
  <name>
   Adidas Hat K-2896
  </name>
  <category>
   Hat
  </category>
  <size>
   L
  </size>
  <color>
   Голубой
  </color>
  <material>
   Вискоза
  </material>
  <price>
   140609
  </price>
  <rating>
   1.28
  </rating>
  <reviews>
   402459
  </reviews>
  <new>
   -
  </new>
  <exclusive>
   no
  </exclusive>
  <sporty>
   no
  </sporty>
 </clothing>
 <clothing>
  <id>
   647292530
  </id>
  <name>
   Adidas Sweater K-3480
  </name>
  <category>
   Sweater
  </category>
  <size>
   L
  </size>
  <color>
   Синий
  </color>
  <material>
   Лен
  </material>
  <price>
   523303
  </price>
  <rating>
   3.55
  </rating>
  <reviews>
   256945
  </reviews>
  <new>
   -
  </new>
 </clothing>
 <clothing>
  <id>
   941446413
  </id>
  <name>
   Vans Dress P-8222
  </name>
  <category>
   Dress
  </category>
  <size>
   XL
  </size>
  <color>
   Желтый
  </color>
  <material>
   Шерсть
  </material>
  <price>
   171524
  </price>
  <rating>
   1.45
  </rating>
  <reviews>
   171484
  </reviews>
  <exclusive>
   no
  </exclusive>
 </clothing>
 <clothing>
  <id>
   399765125
  </id>
  <name>
   Converse Skirt O-2623
  </name>
  <category>
   Skirt
  </category>
  <size>
   L
  </size>
  <color>
   Голубой
  </color>
  <material>
   Вискоза
  </material>
  <price>
   474753
  </price>
  <rating>
   3.76
  </rating>
  <reviews>
   241807
  </reviews>
  <new>
   -
  </new>
  <exclusive>
   no
  </exclusive>
  <sporty>
   no
  </sporty>
 </clothing>
</clothing-items>
